nsepythonserver/__init__.py
nsepythonserver/rahu.py
nsepythonserver-2.97.dist-info/licenses/LICENSE
nsepythonserver-2.97.dist-info/METADATA
nsepythonserver-2.97.dist-info/WHEEL
nsepythonserver-2.97.dist-info/top_level.txt
nsepythonserver-2.97.dist-info/RECORD
