Metadata-Version: 2.4
Name: nsepythonserver
Version: 2.97
Summary: Python library for NSE India APIs
Home-page: https://github.com/aeron7/nsepythonserver
Author: Aeron7
Author-email: dexter@unofficed.com
License: GNU
Keywords: nseindia,nse,python,sdk,trading,stock markets
Classifier: Intended Audience :: Developers
Classifier: Natural Language :: English
Classifier: Operating System :: OS Independent
Classifier: Programming Language :: Python
Classifier: Programming Language :: Python :: 3
Classifier: Programming Language :: Python :: Implementation :: PyPy
Classifier: Topic :: Software Development :: Libraries :: Python Modules
License-File: LICENSE
Requires-Dist: requests
Requires-Dist: pandas
Requires-Dist: scipy
Dynamic: author
Dynamic: author-email
Dynamic: classifier
Dynamic: description
Dynamic: description-content-type
Dynamic: home-page
Dynamic: keywords
Dynamic: license
Dynamic: license-file
Dynamic: requires-dist
Dynamic: summary
